<?xml version="1.0" encoding="UTF-8"?>
<export version="D">
  <design>
    <source>/home/harald/Basteln/ThermoLight/thermolight/thermolight.sch</source>
    <date>Mo 09 Apr 2018 22:05:31 CEST</date>
    <tool>Eeschema 4.0.7-e2-6376~58~ubuntu16.04.1</tool>
    <sheet number="1" name="/" tstamps="/">
      <title_block>
        <title>ThermoLight</title>
        <company/>
        <rev>01</rev>
        <date>2018-03-15</date>
        <source>thermolight.sch</source>
        <comment number="1" value=""/>
        <comment number="2" value=""/>
        <comment number="3" value=""/>
        <comment number="4" value=""/>
      </title_block>
    </sheet>
    <sheet number="2" name="/esp-12s/" tstamps="/5A95D2E3/">
      <title_block>
        <title>ESP-12S</title>
        <company/>
        <rev>1</rev>
        <date/>
        <source>esp-12s.sch</source>
        <comment number="1" value=""/>
        <comment number="2" value=""/>
        <comment number="3" value=""/>
        <comment number="4" value=""/>
      </title_block>
    </sheet>
    <sheet number="3" name="/AP2112/" tstamps="/5A961788/">
      <title_block>
        <title>AP2112</title>
        <company/>
        <rev>1</rev>
        <date/>
        <source>AP2112.sch</source>
        <comment number="1" value="5V to 3V3 voltage regulator"/>
        <comment number="2" value="600mA max."/>
        <comment number="3" value=""/>
        <comment number="4" value=""/>
      </title_block>
    </sheet>
    <sheet number="4" name="/WS2812B_01/" tstamps="/5A97371A/">
      <title_block>
        <title>WS2812B incl. supporting circuitry</title>
        <company/>
        <rev>1</rev>
        <date/>
        <source>ws2812b.sch</source>
        <comment number="1" value="Din of first pixel should be protected by ~470R"/>
        <comment number="2" value="VCC &amp; GND should be buffered by ~1000u"/>
        <comment number="3" value=""/>
        <comment number="4" value=""/>
      </title_block>
    </sheet>
    <sheet number="5" name="/WS2812B_02/" tstamps="/5A97592F/">
      <title_block>
        <title>WS2812B incl. supporting circuitry</title>
        <company/>
        <rev>1</rev>
        <date/>
        <source>ws2812b.sch</source>
        <comment number="1" value="Din of first pixel should be protected by ~470R"/>
        <comment number="2" value="VCC &amp; GND should be buffered by ~1000u"/>
        <comment number="3" value=""/>
        <comment number="4" value=""/>
      </title_block>
    </sheet>
    <sheet number="6" name="/WS2812B_03/" tstamps="/5A975C0F/">
      <title_block>
        <title>WS2812B incl. supporting circuitry</title>
        <company/>
        <rev>1</rev>
        <date/>
        <source>ws2812b.sch</source>
        <comment number="1" value="Din of first pixel should be protected by ~470R"/>
        <comment number="2" value="VCC &amp; GND should be buffered by ~1000u"/>
        <comment number="3" value=""/>
        <comment number="4" value=""/>
      </title_block>
    </sheet>
    <sheet number="7" name="/WS2812B_04/" tstamps="/5A975C13/">
      <title_block>
        <title>WS2812B incl. supporting circuitry</title>
        <company/>
        <rev>1</rev>
        <date/>
        <source>ws2812b.sch</source>
        <comment number="1" value="Din of first pixel should be protected by ~470R"/>
        <comment number="2" value="VCC &amp; GND should be buffered by ~1000u"/>
        <comment number="3" value=""/>
        <comment number="4" value=""/>
      </title_block>
    </sheet>
    <sheet number="8" name="/WS2812B_05/" tstamps="/5A9777A7/">
      <title_block>
        <title>WS2812B incl. supporting circuitry</title>
        <company/>
        <rev>1</rev>
        <date/>
        <source>ws2812b.sch</source>
        <comment number="1" value="Din of first pixel should be protected by ~470R"/>
        <comment number="2" value="VCC &amp; GND should be buffered by ~1000u"/>
        <comment number="3" value=""/>
        <comment number="4" value=""/>
      </title_block>
    </sheet>
    <sheet number="9" name="/WS2812B_06/" tstamps="/5A9777AB/">
      <title_block>
        <title>WS2812B incl. supporting circuitry</title>
        <company/>
        <rev>1</rev>
        <date/>
        <source>ws2812b.sch</source>
        <comment number="1" value="Din of first pixel should be protected by ~470R"/>
        <comment number="2" value="VCC &amp; GND should be buffered by ~1000u"/>
        <comment number="3" value=""/>
        <comment number="4" value=""/>
      </title_block>
    </sheet>
    <sheet number="10" name="/WS2812B_07/" tstamps="/5A9777AF/">
      <title_block>
        <title>WS2812B incl. supporting circuitry</title>
        <company/>
        <rev>1</rev>
        <date/>
        <source>ws2812b.sch</source>
        <comment number="1" value="Din of first pixel should be protected by ~470R"/>
        <comment number="2" value="VCC &amp; GND should be buffered by ~1000u"/>
        <comment number="3" value=""/>
        <comment number="4" value=""/>
      </title_block>
    </sheet>
    <sheet number="11" name="/WS2812B_08/" tstamps="/5A9777B3/">
      <title_block>
        <title>WS2812B incl. supporting circuitry</title>
        <company/>
        <rev>1</rev>
        <date/>
        <source>ws2812b.sch</source>
        <comment number="1" value="Din of first pixel should be protected by ~470R"/>
        <comment number="2" value="VCC &amp; GND should be buffered by ~1000u"/>
        <comment number="3" value=""/>
        <comment number="4" value=""/>
      </title_block>
    </sheet>
    <sheet number="12" name="/WS2812B_09/" tstamps="/5A97932F/">
      <title_block>
        <title>WS2812B incl. supporting circuitry</title>
        <company/>
        <rev>1</rev>
        <date/>
        <source>ws2812b.sch</source>
        <comment number="1" value="Din of first pixel should be protected by ~470R"/>
        <comment number="2" value="VCC &amp; GND should be buffered by ~1000u"/>
        <comment number="3" value=""/>
        <comment number="4" value=""/>
      </title_block>
    </sheet>
    <sheet number="13" name="/WS2812B_10/" tstamps="/5A979333/">
      <title_block>
        <title>WS2812B incl. supporting circuitry</title>
        <company/>
        <rev>1</rev>
        <date/>
        <source>ws2812b.sch</source>
        <comment number="1" value="Din of first pixel should be protected by ~470R"/>
        <comment number="2" value="VCC &amp; GND should be buffered by ~1000u"/>
        <comment number="3" value=""/>
        <comment number="4" value=""/>
      </title_block>
    </sheet>
    <sheet number="14" name="/WS2812B_11/" tstamps="/5A979337/">
      <title_block>
        <title>WS2812B incl. supporting circuitry</title>
        <company/>
        <rev>1</rev>
        <date/>
        <source>ws2812b.sch</source>
        <comment number="1" value="Din of first pixel should be protected by ~470R"/>
        <comment number="2" value="VCC &amp; GND should be buffered by ~1000u"/>
        <comment number="3" value=""/>
        <comment number="4" value=""/>
      </title_block>
    </sheet>
    <sheet number="15" name="/WS2812B_12/" tstamps="/5A97933B/">
      <title_block>
        <title>WS2812B incl. supporting circuitry</title>
        <company/>
        <rev>1</rev>
        <date/>
        <source>ws2812b.sch</source>
        <comment number="1" value="Din of first pixel should be protected by ~470R"/>
        <comment number="2" value="VCC &amp; GND should be buffered by ~1000u"/>
        <comment number="3" value=""/>
        <comment number="4" value=""/>
      </title_block>
    </sheet>
    <sheet number="16" name="/WS2812B_13/" tstamps="/5A97933F/">
      <title_block>
        <title>WS2812B incl. supporting circuitry</title>
        <company/>
        <rev>1</rev>
        <date/>
        <source>ws2812b.sch</source>
        <comment number="1" value="Din of first pixel should be protected by ~470R"/>
        <comment number="2" value="VCC &amp; GND should be buffered by ~1000u"/>
        <comment number="3" value=""/>
        <comment number="4" value=""/>
      </title_block>
    </sheet>
    <sheet number="17" name="/WS2812B_14/" tstamps="/5A979343/">
      <title_block>
        <title>WS2812B incl. supporting circuitry</title>
        <company/>
        <rev>1</rev>
        <date/>
        <source>ws2812b.sch</source>
        <comment number="1" value="Din of first pixel should be protected by ~470R"/>
        <comment number="2" value="VCC &amp; GND should be buffered by ~1000u"/>
        <comment number="3" value=""/>
        <comment number="4" value=""/>
      </title_block>
    </sheet>
    <sheet number="18" name="/WS2812B_15/" tstamps="/5A979347/">
      <title_block>
        <title>WS2812B incl. supporting circuitry</title>
        <company/>
        <rev>1</rev>
        <date/>
        <source>ws2812b.sch</source>
        <comment number="1" value="Din of first pixel should be protected by ~470R"/>
        <comment number="2" value="VCC &amp; GND should be buffered by ~1000u"/>
        <comment number="3" value=""/>
        <comment number="4" value=""/>
      </title_block>
    </sheet>
    <sheet number="19" name="/WS2812B_16/" tstamps="/5A97934B/">
      <title_block>
        <title>WS2812B incl. supporting circuitry</title>
        <company/>
        <rev>1</rev>
        <date/>
        <source>ws2812b.sch</source>
        <comment number="1" value="Din of first pixel should be protected by ~470R"/>
        <comment number="2" value="VCC &amp; GND should be buffered by ~1000u"/>
        <comment number="3" value=""/>
        <comment number="4" value=""/>
      </title_block>
    </sheet>
    <sheet number="20" name="/WS2812B_17/" tstamps="/5A97E257/">
      <title_block>
        <title>WS2812B incl. supporting circuitry</title>
        <company/>
        <rev>1</rev>
        <date/>
        <source>ws2812b.sch</source>
        <comment number="1" value="Din of first pixel should be protected by ~470R"/>
        <comment number="2" value="VCC &amp; GND should be buffered by ~1000u"/>
        <comment number="3" value=""/>
        <comment number="4" value=""/>
      </title_block>
    </sheet>
    <sheet number="21" name="/WS2812B_18/" tstamps="/5A97E25B/">
      <title_block>
        <title>WS2812B incl. supporting circuitry</title>
        <company/>
        <rev>1</rev>
        <date/>
        <source>ws2812b.sch</source>
        <comment number="1" value="Din of first pixel should be protected by ~470R"/>
        <comment number="2" value="VCC &amp; GND should be buffered by ~1000u"/>
        <comment number="3" value=""/>
        <comment number="4" value=""/>
      </title_block>
    </sheet>
    <sheet number="22" name="/WS2812B_19/" tstamps="/5A97E25F/">
      <title_block>
        <title>WS2812B incl. supporting circuitry</title>
        <company/>
        <rev>1</rev>
        <date/>
        <source>ws2812b.sch</source>
        <comment number="1" value="Din of first pixel should be protected by ~470R"/>
        <comment number="2" value="VCC &amp; GND should be buffered by ~1000u"/>
        <comment number="3" value=""/>
        <comment number="4" value=""/>
      </title_block>
    </sheet>
    <sheet number="23" name="/WS2812B_20/" tstamps="/5A97E263/">
      <title_block>
        <title>WS2812B incl. supporting circuitry</title>
        <company/>
        <rev>1</rev>
        <date/>
        <source>ws2812b.sch</source>
        <comment number="1" value="Din of first pixel should be protected by ~470R"/>
        <comment number="2" value="VCC &amp; GND should be buffered by ~1000u"/>
        <comment number="3" value=""/>
        <comment number="4" value=""/>
      </title_block>
    </sheet>
    <sheet number="24" name="/WS2812B_21/" tstamps="/5A97E267/">
      <title_block>
        <title>WS2812B incl. supporting circuitry</title>
        <company/>
        <rev>1</rev>
        <date/>
        <source>ws2812b.sch</source>
        <comment number="1" value="Din of first pixel should be protected by ~470R"/>
        <comment number="2" value="VCC &amp; GND should be buffered by ~1000u"/>
        <comment number="3" value=""/>
        <comment number="4" value=""/>
      </title_block>
    </sheet>
    <sheet number="25" name="/WS2812B_22/" tstamps="/5A985C99/">
      <title_block>
        <title>WS2812B incl. supporting circuitry</title>
        <company/>
        <rev>1</rev>
        <date/>
        <source>ws2812b.sch</source>
        <comment number="1" value="Din of first pixel should be protected by ~470R"/>
        <comment number="2" value="VCC &amp; GND should be buffered by ~1000u"/>
        <comment number="3" value=""/>
        <comment number="4" value=""/>
      </title_block>
    </sheet>
    <sheet number="26" name="/WS2812B_23/" tstamps="/5A985C9D/">
      <title_block>
        <title>WS2812B incl. supporting circuitry</title>
        <company/>
        <rev>1</rev>
        <date/>
        <source>ws2812b.sch</source>
        <comment number="1" value="Din of first pixel should be protected by ~470R"/>
        <comment number="2" value="VCC &amp; GND should be buffered by ~1000u"/>
        <comment number="3" value=""/>
        <comment number="4" value=""/>
      </title_block>
    </sheet>
    <sheet number="27" name="/WS2812B_24/" tstamps="/5A985CA1/">
      <title_block>
        <title>WS2812B incl. supporting circuitry</title>
        <company/>
        <rev>1</rev>
        <date/>
        <source>ws2812b.sch</source>
        <comment number="1" value="Din of first pixel should be protected by ~470R"/>
        <comment number="2" value="VCC &amp; GND should be buffered by ~1000u"/>
        <comment number="3" value=""/>
        <comment number="4" value=""/>
      </title_block>
    </sheet>
    <sheet number="28" name="/WS2812B_32/" tstamps="/5AAA575D/">
      <title_block>
        <title>WS2812B incl. supporting circuitry</title>
        <company/>
        <rev>1</rev>
        <date/>
        <source>ws2812b.sch</source>
        <comment number="1" value="Din of first pixel should be protected by ~470R"/>
        <comment number="2" value="VCC &amp; GND should be buffered by ~1000u"/>
        <comment number="3" value=""/>
        <comment number="4" value=""/>
      </title_block>
    </sheet>
    <sheet number="29" name="/WS2812B_33/" tstamps="/5AAA5761/">
      <title_block>
        <title>WS2812B incl. supporting circuitry</title>
        <company/>
        <rev>1</rev>
        <date/>
        <source>ws2812b.sch</source>
        <comment number="1" value="Din of first pixel should be protected by ~470R"/>
        <comment number="2" value="VCC &amp; GND should be buffered by ~1000u"/>
        <comment number="3" value=""/>
        <comment number="4" value=""/>
      </title_block>
    </sheet>
    <sheet number="30" name="/WS2812B_34/" tstamps="/5AAA5765/">
      <title_block>
        <title>WS2812B incl. supporting circuitry</title>
        <company/>
        <rev>1</rev>
        <date/>
        <source>ws2812b.sch</source>
        <comment number="1" value="Din of first pixel should be protected by ~470R"/>
        <comment number="2" value="VCC &amp; GND should be buffered by ~1000u"/>
        <comment number="3" value=""/>
        <comment number="4" value=""/>
      </title_block>
    </sheet>
    <sheet number="31" name="/WS2812B_35/" tstamps="/5AAA5769/">
      <title_block>
        <title>WS2812B incl. supporting circuitry</title>
        <company/>
        <rev>1</rev>
        <date/>
        <source>ws2812b.sch</source>
        <comment number="1" value="Din of first pixel should be protected by ~470R"/>
        <comment number="2" value="VCC &amp; GND should be buffered by ~1000u"/>
        <comment number="3" value=""/>
        <comment number="4" value=""/>
      </title_block>
    </sheet>
    <sheet number="32" name="/WS2812B_36/" tstamps="/5AAA576D/">
      <title_block>
        <title>WS2812B incl. supporting circuitry</title>
        <company/>
        <rev>1</rev>
        <date/>
        <source>ws2812b.sch</source>
        <comment number="1" value="Din of first pixel should be protected by ~470R"/>
        <comment number="2" value="VCC &amp; GND should be buffered by ~1000u"/>
        <comment number="3" value=""/>
        <comment number="4" value=""/>
      </title_block>
    </sheet>
    <sheet number="33" name="/WS2812B_37/" tstamps="/5AAA5776/">
      <title_block>
        <title>WS2812B incl. supporting circuitry</title>
        <company/>
        <rev>1</rev>
        <date/>
        <source>ws2812b.sch</source>
        <comment number="1" value="Din of first pixel should be protected by ~470R"/>
        <comment number="2" value="VCC &amp; GND should be buffered by ~1000u"/>
        <comment number="3" value=""/>
        <comment number="4" value=""/>
      </title_block>
    </sheet>
    <sheet number="34" name="/WS2812B_38/" tstamps="/5AAA577A/">
      <title_block>
        <title>WS2812B incl. supporting circuitry</title>
        <company/>
        <rev>1</rev>
        <date/>
        <source>ws2812b.sch</source>
        <comment number="1" value="Din of first pixel should be protected by ~470R"/>
        <comment number="2" value="VCC &amp; GND should be buffered by ~1000u"/>
        <comment number="3" value=""/>
        <comment number="4" value=""/>
      </title_block>
    </sheet>
    <sheet number="35" name="/WS2812B_25/" tstamps="/5AAA7755/">
      <title_block>
        <title>WS2812B incl. supporting circuitry</title>
        <company/>
        <rev>1</rev>
        <date/>
        <source>ws2812b.sch</source>
        <comment number="1" value="Din of first pixel should be protected by ~470R"/>
        <comment number="2" value="VCC &amp; GND should be buffered by ~1000u"/>
        <comment number="3" value=""/>
        <comment number="4" value=""/>
      </title_block>
    </sheet>
    <sheet number="36" name="/WS2812B_26/" tstamps="/5AAA7759/">
      <title_block>
        <title>WS2812B incl. supporting circuitry</title>
        <company/>
        <rev>1</rev>
        <date/>
        <source>ws2812b.sch</source>
        <comment number="1" value="Din of first pixel should be protected by ~470R"/>
        <comment number="2" value="VCC &amp; GND should be buffered by ~1000u"/>
        <comment number="3" value=""/>
        <comment number="4" value=""/>
      </title_block>
    </sheet>
    <sheet number="37" name="/WS2812B_27/" tstamps="/5AAA775D/">
      <title_block>
        <title>WS2812B incl. supporting circuitry</title>
        <company/>
        <rev>1</rev>
        <date/>
        <source>ws2812b.sch</source>
        <comment number="1" value="Din of first pixel should be protected by ~470R"/>
        <comment number="2" value="VCC &amp; GND should be buffered by ~1000u"/>
        <comment number="3" value=""/>
        <comment number="4" value=""/>
      </title_block>
    </sheet>
    <sheet number="38" name="/WS2812B_28/" tstamps="/5AAA7761/">
      <title_block>
        <title>WS2812B incl. supporting circuitry</title>
        <company/>
        <rev>1</rev>
        <date/>
        <source>ws2812b.sch</source>
        <comment number="1" value="Din of first pixel should be protected by ~470R"/>
        <comment number="2" value="VCC &amp; GND should be buffered by ~1000u"/>
        <comment number="3" value=""/>
        <comment number="4" value=""/>
      </title_block>
    </sheet>
    <sheet number="39" name="/WS2812B_29/" tstamps="/5AAA7765/">
      <title_block>
        <title>WS2812B incl. supporting circuitry</title>
        <company/>
        <rev>1</rev>
        <date/>
        <source>ws2812b.sch</source>
        <comment number="1" value="Din of first pixel should be protected by ~470R"/>
        <comment number="2" value="VCC &amp; GND should be buffered by ~1000u"/>
        <comment number="3" value=""/>
        <comment number="4" value=""/>
      </title_block>
    </sheet>
    <sheet number="40" name="/WS2812B_30/" tstamps="/5AAA776E/">
      <title_block>
        <title>WS2812B incl. supporting circuitry</title>
        <company/>
        <rev>1</rev>
        <date/>
        <source>ws2812b.sch</source>
        <comment number="1" value="Din of first pixel should be protected by ~470R"/>
        <comment number="2" value="VCC &amp; GND should be buffered by ~1000u"/>
        <comment number="3" value=""/>
        <comment number="4" value=""/>
      </title_block>
    </sheet>
    <sheet number="41" name="/WS2812B_31/" tstamps="/5AAA7772/">
      <title_block>
        <title>WS2812B incl. supporting circuitry</title>
        <company/>
        <rev>1</rev>
        <date/>
        <source>ws2812b.sch</source>
        <comment number="1" value="Din of first pixel should be protected by ~470R"/>
        <comment number="2" value="VCC &amp; GND should be buffered by ~1000u"/>
        <comment number="3" value=""/>
        <comment number="4" value=""/>
      </title_block>
    </sheet>
  </design>
  <components>
    <comp ref="U3">
      <value>74AHCT1G125</value>
      <footprint>TO_SOT_Packages_SMD:SOT-23-5_HandSoldering</footprint>
      <fields>
        <field name="Order#">74AHCT1G125W5</field>
      </fields>
      <libsource lib="mylibrary" part="74AHCT1G125"/>
      <sheetpath names="/" tstamps="/"/>
      <tstamp>5A9718EE</tstamp>
    </comp>
    <comp ref="R7">
      <value>470</value>
      <footprint>Resistors_SMD:R_0603_HandSoldering</footprint>
      <libsource lib="device" part="R"/>
      <sheetpath names="/" tstamps="/"/>
      <tstamp>5A97194D</tstamp>
    </comp>
    <comp ref="C4">
      <value>470u</value>
      <footprint>myfootprints:CP_Radial_D6.3mm_P2.50mm_lying</footprint>
      <libsource lib="device" part="CP"/>
      <sheetpath names="/" tstamps="/"/>
      <tstamp>5A972BB0</tstamp>
    </comp>
    <comp ref="U4">
      <value>iAQ-Core</value>
      <footprint>myfootprints:iAQ-Core</footprint>
      <libsource lib="mylibrary" part="iAQ-Core"/>
      <sheetpath names="/" tstamps="/"/>
      <tstamp>5AAB1260</tstamp>
    </comp>
    <comp ref="R9">
      <value>4k7</value>
      <footprint>Resistors_SMD:R_0603_HandSoldering</footprint>
      <libsource lib="device" part="R"/>
      <sheetpath names="/" tstamps="/"/>
      <tstamp>5AABA3B0</tstamp>
    </comp>
    <comp ref="R8">
      <value>4k7</value>
      <footprint>Resistors_SMD:R_0603_HandSoldering</footprint>
      <libsource lib="device" part="R"/>
      <sheetpath names="/" tstamps="/"/>
      <tstamp>5AABB7BB</tstamp>
    </comp>
    <comp ref="U5">
      <value>SHT31-D</value>
      <footprint>myfootprints:DFN-8-2.5x2.5-0.5mm-handsolder</footprint>
      <libsource lib="mylibrary" part="SHT31-D"/>
      <sheetpath names="/" tstamps="/"/>
      <tstamp>5AAAF035</tstamp>
    </comp>
    <comp ref="C5">
      <value>10u</value>
      <footprint>Capacitors_SMD:C_1206_HandSoldering</footprint>
      <libsource lib="device" part="C"/>
      <sheetpath names="/" tstamps="/"/>
      <tstamp>5AAB94EF</tstamp>
    </comp>
    <comp ref="J2">
      <value>USB_OTG</value>
      <footprint>myfootprints:1051640001</footprint>
      <libsource lib="conn" part="USB_OTG"/>
      <sheetpath names="/" tstamps="/"/>
      <tstamp>5AB264D4</tstamp>
    </comp>
    <comp ref="U6">
      <value>CCS811</value>
      <footprint>myfootprints:LGA_CCS811</footprint>
      <libsource lib="mylibrary" part="CCS811"/>
      <sheetpath names="/" tstamps="/"/>
      <tstamp>5AB46235</tstamp>
    </comp>
    <comp ref="C44">
      <value>10u</value>
      <footprint>Capacitors_SMD:C_1206_HandSoldering</footprint>
      <libsource lib="device" part="C"/>
      <sheetpath names="/" tstamps="/"/>
      <tstamp>5AB49879</tstamp>
    </comp>
    <comp ref="R10">
      <value>4k7</value>
      <footprint>Resistors_SMD:R_0603_HandSoldering</footprint>
      <libsource lib="device" part="R"/>
      <sheetpath names="/" tstamps="/"/>
      <tstamp>5AB508CC</tstamp>
    </comp>
    <comp ref="C45">
      <value>470u</value>
      <footprint>myfootprints:CP_Radial_D6.3mm_P2.50mm_lying</footprint>
      <libsource lib="device" part="CP"/>
      <sheetpath names="/" tstamps="/"/>
      <tstamp>5AC17317</tstamp>
    </comp>
    <comp ref="U2">
      <value>ESP-12</value>
      <footprint>myfootprints:ESP-12S_SMD</footprint>
      <libsource lib="ESP8266" part="ESP-12"/>
      <sheetpath names="/esp-12s/" tstamps="/5A95D2E3/"/>
      <tstamp>59B98CD1</tstamp>
    </comp>
    <comp ref="R2">
      <value>10k</value>
      <footprint>Resistors_SMD:R_0603_HandSoldering</footprint>
      <libsource lib="device" part="R"/>
      <sheetpath names="/esp-12s/" tstamps="/5A95D2E3/"/>
      <tstamp>59B98CD7</tstamp>
    </comp>
    <comp ref="R1">
      <value>10k</value>
      <footprint>Resistors_SMD:R_0603_HandSoldering</footprint>
      <libsource lib="device" part="R"/>
      <sheetpath names="/esp-12s/" tstamps="/5A95D2E3/"/>
      <tstamp>59B98CD8</tstamp>
    </comp>
    <comp ref="RST1">
      <value>TL3315NF160Q</value>
      <footprint>myfootprints:TL3315</footprint>
      <libsource lib="switches" part="SW_Push"/>
      <sheetpath names="/esp-12s/" tstamps="/5A95D2E3/"/>
      <tstamp>59B98CD9</tstamp>
    </comp>
    <comp ref="R4">
      <value>10k</value>
      <footprint>Resistors_SMD:R_0603_HandSoldering</footprint>
      <libsource lib="device" part="R"/>
      <sheetpath names="/esp-12s/" tstamps="/5A95D2E3/"/>
      <tstamp>59B98CDC</tstamp>
    </comp>
    <comp ref="PROG1">
      <value>TL3315NF160Q</value>
      <footprint>myfootprints:TL3315</footprint>
      <libsource lib="switches" part="SW_Push"/>
      <sheetpath names="/esp-12s/" tstamps="/5A95D2E3/"/>
      <tstamp>59B98CDD</tstamp>
    </comp>
    <comp ref="R5">
      <value>10k</value>
      <footprint>Resistors_SMD:R_0603_HandSoldering</footprint>
      <libsource lib="device" part="R"/>
      <sheetpath names="/esp-12s/" tstamps="/5A95D2E3/"/>
      <tstamp>59B98CDF</tstamp>
    </comp>
    <comp ref="R6">
      <value>10k</value>
      <footprint>Resistors_SMD:R_0603_HandSoldering</footprint>
      <libsource lib="device" part="R"/>
      <sheetpath names="/esp-12s/" tstamps="/5A95D2E3/"/>
      <tstamp>59B98CE0</tstamp>
    </comp>
    <comp ref="C2">
      <value>10u</value>
      <footprint>Capacitors_SMD:C_1206_HandSoldering</footprint>
      <libsource lib="device" part="C"/>
      <sheetpath names="/esp-12s/" tstamps="/5A95D2E3/"/>
      <tstamp>59B98CE3</tstamp>
    </comp>
    <comp ref="J1">
      <value>952-1951-ND</value>
      <footprint>Pin_Headers:Pin_Header_Straight_1x03_Pitch2.54mm_SMD_Pin1Right</footprint>
      <libsource lib="conn" part="Conn_01x03"/>
      <sheetpath names="/esp-12s/" tstamps="/5A95D2E3/"/>
      <tstamp>5AC14302</tstamp>
    </comp>
    <comp ref="R3">
      <value>10k</value>
      <footprint>Resistors_SMD:R_0603_HandSoldering</footprint>
      <libsource lib="device" part="R"/>
      <sheetpath names="/AP2112/" tstamps="/5A961788/"/>
      <tstamp>59C3283F</tstamp>
    </comp>
    <comp ref="C3">
      <value>10u</value>
      <footprint>Capacitors_SMD:C_1206_HandSoldering</footprint>
      <libsource lib="device" part="C"/>
      <sheetpath names="/AP2112/" tstamps="/5A961788/"/>
      <tstamp>59C330E6</tstamp>
    </comp>
    <comp ref="C1">
      <value>10u</value>
      <footprint>Capacitors_SMD:C_1206_HandSoldering</footprint>
      <libsource lib="device" part="C"/>
      <sheetpath names="/AP2112/" tstamps="/5A961788/"/>
      <tstamp>59C33602</tstamp>
    </comp>
    <comp ref="U1">
      <value>AP2112</value>
      <footprint>TO_SOT_Packages_SMD:SOT-23-5_HandSoldering</footprint>
      <libsource lib="mylibrary" part="AP2112"/>
      <sheetpath names="/AP2112/" tstamps="/5A961788/"/>
      <tstamp>59C33E1A</tstamp>
    </comp>
    <comp ref="LED1">
      <value>WS2812B</value>
      <footprint>LEDs:LED_WS2812B-PLCC4</footprint>
      <libsource lib="Worldsemi" part="WS2812B"/>
      <sheetpath names="/WS2812B_01/" tstamps="/5A97371A/"/>
      <tstamp>5A973791</tstamp>
    </comp>
    <comp ref="C6">
      <value>0.1u</value>
      <footprint>Capacitors_SMD:C_0603_HandSoldering</footprint>
      <libsource lib="device" part="C"/>
      <sheetpath names="/WS2812B_01/" tstamps="/5A97371A/"/>
      <tstamp>5A9737EE</tstamp>
    </comp>
    <comp ref="LED2">
      <value>WS2812B</value>
      <footprint>LEDs:LED_WS2812B-PLCC4</footprint>
      <libsource lib="Worldsemi" part="WS2812B"/>
      <sheetpath names="/WS2812B_02/" tstamps="/5A97592F/"/>
      <tstamp>5A973791</tstamp>
    </comp>
    <comp ref="C7">
      <value>0.1u</value>
      <footprint>Capacitors_SMD:C_0603_HandSoldering</footprint>
      <libsource lib="device" part="C"/>
      <sheetpath names="/WS2812B_02/" tstamps="/5A97592F/"/>
      <tstamp>5A9737EE</tstamp>
    </comp>
    <comp ref="LED3">
      <value>WS2812B</value>
      <footprint>LEDs:LED_WS2812B-PLCC4</footprint>
      <libsource lib="Worldsemi" part="WS2812B"/>
      <sheetpath names="/WS2812B_03/" tstamps="/5A975C0F/"/>
      <tstamp>5A973791</tstamp>
    </comp>
    <comp ref="C8">
      <value>0.1u</value>
      <footprint>Capacitors_SMD:C_0603_HandSoldering</footprint>
      <libsource lib="device" part="C"/>
      <sheetpath names="/WS2812B_03/" tstamps="/5A975C0F/"/>
      <tstamp>5A9737EE</tstamp>
    </comp>
    <comp ref="LED4">
      <value>WS2812B</value>
      <footprint>LEDs:LED_WS2812B-PLCC4</footprint>
      <libsource lib="Worldsemi" part="WS2812B"/>
      <sheetpath names="/WS2812B_04/" tstamps="/5A975C13/"/>
      <tstamp>5A973791</tstamp>
    </comp>
    <comp ref="C9">
      <value>0.1u</value>
      <footprint>Capacitors_SMD:C_0603_HandSoldering</footprint>
      <libsource lib="device" part="C"/>
      <sheetpath names="/WS2812B_04/" tstamps="/5A975C13/"/>
      <tstamp>5A9737EE</tstamp>
    </comp>
    <comp ref="LED5">
      <value>WS2812B</value>
      <footprint>LEDs:LED_WS2812B-PLCC4</footprint>
      <libsource lib="Worldsemi" part="WS2812B"/>
      <sheetpath names="/WS2812B_05/" tstamps="/5A9777A7/"/>
      <tstamp>5A973791</tstamp>
    </comp>
    <comp ref="C10">
      <value>0.1u</value>
      <footprint>Capacitors_SMD:C_0603_HandSoldering</footprint>
      <libsource lib="device" part="C"/>
      <sheetpath names="/WS2812B_05/" tstamps="/5A9777A7/"/>
      <tstamp>5A9737EE</tstamp>
    </comp>
    <comp ref="LED6">
      <value>WS2812B</value>
      <footprint>LEDs:LED_WS2812B-PLCC4</footprint>
      <libsource lib="Worldsemi" part="WS2812B"/>
      <sheetpath names="/WS2812B_06/" tstamps="/5A9777AB/"/>
      <tstamp>5A973791</tstamp>
    </comp>
    <comp ref="C11">
      <value>0.1u</value>
      <footprint>Capacitors_SMD:C_0603_HandSoldering</footprint>
      <libsource lib="device" part="C"/>
      <sheetpath names="/WS2812B_06/" tstamps="/5A9777AB/"/>
      <tstamp>5A9737EE</tstamp>
    </comp>
    <comp ref="LED7">
      <value>WS2812B</value>
      <footprint>LEDs:LED_WS2812B-PLCC4</footprint>
      <libsource lib="Worldsemi" part="WS2812B"/>
      <sheetpath names="/WS2812B_07/" tstamps="/5A9777AF/"/>
      <tstamp>5A973791</tstamp>
    </comp>
    <comp ref="C12">
      <value>0.1u</value>
      <footprint>Capacitors_SMD:C_0603_HandSoldering</footprint>
      <libsource lib="device" part="C"/>
      <sheetpath names="/WS2812B_07/" tstamps="/5A9777AF/"/>
      <tstamp>5A9737EE</tstamp>
    </comp>
    <comp ref="LED8">
      <value>WS2812B</value>
      <footprint>LEDs:LED_WS2812B-PLCC4</footprint>
      <libsource lib="Worldsemi" part="WS2812B"/>
      <sheetpath names="/WS2812B_08/" tstamps="/5A9777B3/"/>
      <tstamp>5A973791</tstamp>
    </comp>
    <comp ref="C13">
      <value>0.1u</value>
      <footprint>Capacitors_SMD:C_0603_HandSoldering</footprint>
      <libsource lib="device" part="C"/>
      <sheetpath names="/WS2812B_08/" tstamps="/5A9777B3/"/>
      <tstamp>5A9737EE</tstamp>
    </comp>
    <comp ref="LED9">
      <value>WS2812B</value>
      <footprint>LEDs:LED_WS2812B-PLCC4</footprint>
      <libsource lib="Worldsemi" part="WS2812B"/>
      <sheetpath names="/WS2812B_09/" tstamps="/5A97932F/"/>
      <tstamp>5A973791</tstamp>
    </comp>
    <comp ref="C14">
      <value>0.1u</value>
      <footprint>Capacitors_SMD:C_0603_HandSoldering</footprint>
      <libsource lib="device" part="C"/>
      <sheetpath names="/WS2812B_09/" tstamps="/5A97932F/"/>
      <tstamp>5A9737EE</tstamp>
    </comp>
    <comp ref="LED10">
      <value>WS2812B</value>
      <footprint>LEDs:LED_WS2812B-PLCC4</footprint>
      <libsource lib="Worldsemi" part="WS2812B"/>
      <sheetpath names="/WS2812B_10/" tstamps="/5A979333/"/>
      <tstamp>5A973791</tstamp>
    </comp>
    <comp ref="C15">
      <value>0.1u</value>
      <footprint>Capacitors_SMD:C_0603_HandSoldering</footprint>
      <libsource lib="device" part="C"/>
      <sheetpath names="/WS2812B_10/" tstamps="/5A979333/"/>
      <tstamp>5A9737EE</tstamp>
    </comp>
    <comp ref="LED11">
      <value>WS2812B</value>
      <footprint>LEDs:LED_WS2812B-PLCC4</footprint>
      <libsource lib="Worldsemi" part="WS2812B"/>
      <sheetpath names="/WS2812B_11/" tstamps="/5A979337/"/>
      <tstamp>5A973791</tstamp>
    </comp>
    <comp ref="C16">
      <value>0.1u</value>
      <footprint>Capacitors_SMD:C_0603_HandSoldering</footprint>
      <libsource lib="device" part="C"/>
      <sheetpath names="/WS2812B_11/" tstamps="/5A979337/"/>
      <tstamp>5A9737EE</tstamp>
    </comp>
    <comp ref="LED12">
      <value>WS2812B</value>
      <footprint>LEDs:LED_WS2812B-PLCC4</footprint>
      <libsource lib="Worldsemi" part="WS2812B"/>
      <sheetpath names="/WS2812B_12/" tstamps="/5A97933B/"/>
      <tstamp>5A973791</tstamp>
    </comp>
    <comp ref="C17">
      <value>0.1u</value>
      <footprint>Capacitors_SMD:C_0603_HandSoldering</footprint>
      <libsource lib="device" part="C"/>
      <sheetpath names="/WS2812B_12/" tstamps="/5A97933B/"/>
      <tstamp>5A9737EE</tstamp>
    </comp>
    <comp ref="LED13">
      <value>WS2812B</value>
      <footprint>LEDs:LED_WS2812B-PLCC4</footprint>
      <libsource lib="Worldsemi" part="WS2812B"/>
      <sheetpath names="/WS2812B_13/" tstamps="/5A97933F/"/>
      <tstamp>5A973791</tstamp>
    </comp>
    <comp ref="C18">
      <value>0.1u</value>
      <footprint>Capacitors_SMD:C_0603_HandSoldering</footprint>
      <libsource lib="device" part="C"/>
      <sheetpath names="/WS2812B_13/" tstamps="/5A97933F/"/>
      <tstamp>5A9737EE</tstamp>
    </comp>
    <comp ref="LED14">
      <value>WS2812B</value>
      <footprint>LEDs:LED_WS2812B-PLCC4</footprint>
      <libsource lib="Worldsemi" part="WS2812B"/>
      <sheetpath names="/WS2812B_14/" tstamps="/5A979343/"/>
      <tstamp>5A973791</tstamp>
    </comp>
    <comp ref="C19">
      <value>0.1u</value>
      <footprint>Capacitors_SMD:C_0603_HandSoldering</footprint>
      <libsource lib="device" part="C"/>
      <sheetpath names="/WS2812B_14/" tstamps="/5A979343/"/>
      <tstamp>5A9737EE</tstamp>
    </comp>
    <comp ref="LED15">
      <value>WS2812B</value>
      <footprint>LEDs:LED_WS2812B-PLCC4</footprint>
      <libsource lib="Worldsemi" part="WS2812B"/>
      <sheetpath names="/WS2812B_15/" tstamps="/5A979347/"/>
      <tstamp>5A973791</tstamp>
    </comp>
    <comp ref="C20">
      <value>0.1u</value>
      <footprint>Capacitors_SMD:C_0603_HandSoldering</footprint>
      <libsource lib="device" part="C"/>
      <sheetpath names="/WS2812B_15/" tstamps="/5A979347/"/>
      <tstamp>5A9737EE</tstamp>
    </comp>
    <comp ref="LED16">
      <value>WS2812B</value>
      <footprint>LEDs:LED_WS2812B-PLCC4</footprint>
      <libsource lib="Worldsemi" part="WS2812B"/>
      <sheetpath names="/WS2812B_16/" tstamps="/5A97934B/"/>
      <tstamp>5A973791</tstamp>
    </comp>
    <comp ref="C21">
      <value>0.1u</value>
      <footprint>Capacitors_SMD:C_0603_HandSoldering</footprint>
      <libsource lib="device" part="C"/>
      <sheetpath names="/WS2812B_16/" tstamps="/5A97934B/"/>
      <tstamp>5A9737EE</tstamp>
    </comp>
    <comp ref="LED17">
      <value>WS2812B</value>
      <footprint>LEDs:LED_WS2812B-PLCC4</footprint>
      <libsource lib="Worldsemi" part="WS2812B"/>
      <sheetpath names="/WS2812B_17/" tstamps="/5A97E257/"/>
      <tstamp>5A973791</tstamp>
    </comp>
    <comp ref="C22">
      <value>0.1u</value>
      <footprint>Capacitors_SMD:C_0603_HandSoldering</footprint>
      <libsource lib="device" part="C"/>
      <sheetpath names="/WS2812B_17/" tstamps="/5A97E257/"/>
      <tstamp>5A9737EE</tstamp>
    </comp>
    <comp ref="LED18">
      <value>WS2812B</value>
      <footprint>LEDs:LED_WS2812B-PLCC4</footprint>
      <libsource lib="Worldsemi" part="WS2812B"/>
      <sheetpath names="/WS2812B_18/" tstamps="/5A97E25B/"/>
      <tstamp>5A973791</tstamp>
    </comp>
    <comp ref="C23">
      <value>0.1u</value>
      <footprint>Capacitors_SMD:C_0603_HandSoldering</footprint>
      <libsource lib="device" part="C"/>
      <sheetpath names="/WS2812B_18/" tstamps="/5A97E25B/"/>
      <tstamp>5A9737EE</tstamp>
    </comp>
    <comp ref="LED19">
      <value>WS2812B</value>
      <footprint>LEDs:LED_WS2812B-PLCC4</footprint>
      <libsource lib="Worldsemi" part="WS2812B"/>
      <sheetpath names="/WS2812B_19/" tstamps="/5A97E25F/"/>
      <tstamp>5A973791</tstamp>
    </comp>
    <comp ref="C24">
      <value>0.1u</value>
      <footprint>Capacitors_SMD:C_0603_HandSoldering</footprint>
      <libsource lib="device" part="C"/>
      <sheetpath names="/WS2812B_19/" tstamps="/5A97E25F/"/>
      <tstamp>5A9737EE</tstamp>
    </comp>
    <comp ref="LED20">
      <value>WS2812B</value>
      <footprint>LEDs:LED_WS2812B-PLCC4</footprint>
      <libsource lib="Worldsemi" part="WS2812B"/>
      <sheetpath names="/WS2812B_20/" tstamps="/5A97E263/"/>
      <tstamp>5A973791</tstamp>
    </comp>
    <comp ref="C25">
      <value>0.1u</value>
      <footprint>Capacitors_SMD:C_0603_HandSoldering</footprint>
      <libsource lib="device" part="C"/>
      <sheetpath names="/WS2812B_20/" tstamps="/5A97E263/"/>
      <tstamp>5A9737EE</tstamp>
    </comp>
    <comp ref="LED21">
      <value>WS2812B</value>
      <footprint>LEDs:LED_WS2812B-PLCC4</footprint>
      <libsource lib="Worldsemi" part="WS2812B"/>
      <sheetpath names="/WS2812B_21/" tstamps="/5A97E267/"/>
      <tstamp>5A973791</tstamp>
    </comp>
    <comp ref="C26">
      <value>0.1u</value>
      <footprint>Capacitors_SMD:C_0603_HandSoldering</footprint>
      <libsource lib="device" part="C"/>
      <sheetpath names="/WS2812B_21/" tstamps="/5A97E267/"/>
      <tstamp>5A9737EE</tstamp>
    </comp>
    <comp ref="LED22">
      <value>WS2812B</value>
      <footprint>LEDs:LED_WS2812B-PLCC4</footprint>
      <libsource lib="Worldsemi" part="WS2812B"/>
      <sheetpath names="/WS2812B_22/" tstamps="/5A985C99/"/>
      <tstamp>5A973791</tstamp>
    </comp>
    <comp ref="C27">
      <value>0.1u</value>
      <footprint>Capacitors_SMD:C_0603_HandSoldering</footprint>
      <libsource lib="device" part="C"/>
      <sheetpath names="/WS2812B_22/" tstamps="/5A985C99/"/>
      <tstamp>5A9737EE</tstamp>
    </comp>
    <comp ref="LED23">
      <value>WS2812B</value>
      <footprint>LEDs:LED_WS2812B-PLCC4</footprint>
      <libsource lib="Worldsemi" part="WS2812B"/>
      <sheetpath names="/WS2812B_23/" tstamps="/5A985C9D/"/>
      <tstamp>5A973791</tstamp>
    </comp>
    <comp ref="C28">
      <value>0.1u</value>
      <footprint>Capacitors_SMD:C_0603_HandSoldering</footprint>
      <libsource lib="device" part="C"/>
      <sheetpath names="/WS2812B_23/" tstamps="/5A985C9D/"/>
      <tstamp>5A9737EE</tstamp>
    </comp>
    <comp ref="LED24">
      <value>WS2812B</value>
      <footprint>LEDs:LED_WS2812B-PLCC4</footprint>
      <libsource lib="Worldsemi" part="WS2812B"/>
      <sheetpath names="/WS2812B_24/" tstamps="/5A985CA1/"/>
      <tstamp>5A973791</tstamp>
    </comp>
    <comp ref="C29">
      <value>0.1u</value>
      <footprint>Capacitors_SMD:C_0603_HandSoldering</footprint>
      <libsource lib="device" part="C"/>
      <sheetpath names="/WS2812B_24/" tstamps="/5A985CA1/"/>
      <tstamp>5A9737EE</tstamp>
    </comp>
    <comp ref="LED25">
      <value>WS2812B</value>
      <footprint>LEDs:LED_WS2812B-PLCC4</footprint>
      <libsource lib="Worldsemi" part="WS2812B"/>
      <sheetpath names="/WS2812B_32/" tstamps="/5AAA575D/"/>
      <tstamp>5A973791</tstamp>
    </comp>
    <comp ref="C30">
      <value>0.1u</value>
      <footprint>Capacitors_SMD:C_0603_HandSoldering</footprint>
      <libsource lib="device" part="C"/>
      <sheetpath names="/WS2812B_32/" tstamps="/5AAA575D/"/>
      <tstamp>5A9737EE</tstamp>
    </comp>
    <comp ref="LED26">
      <value>WS2812B</value>
      <footprint>LEDs:LED_WS2812B-PLCC4</footprint>
      <libsource lib="Worldsemi" part="WS2812B"/>
      <sheetpath names="/WS2812B_33/" tstamps="/5AAA5761/"/>
      <tstamp>5A973791</tstamp>
    </comp>
    <comp ref="C31">
      <value>0.1u</value>
      <footprint>Capacitors_SMD:C_0603_HandSoldering</footprint>
      <libsource lib="device" part="C"/>
      <sheetpath names="/WS2812B_33/" tstamps="/5AAA5761/"/>
      <tstamp>5A9737EE</tstamp>
    </comp>
    <comp ref="LED27">
      <value>WS2812B</value>
      <footprint>LEDs:LED_WS2812B-PLCC4</footprint>
      <libsource lib="Worldsemi" part="WS2812B"/>
      <sheetpath names="/WS2812B_34/" tstamps="/5AAA5765/"/>
      <tstamp>5A973791</tstamp>
    </comp>
    <comp ref="C32">
      <value>0.1u</value>
      <footprint>Capacitors_SMD:C_0603_HandSoldering</footprint>
      <libsource lib="device" part="C"/>
      <sheetpath names="/WS2812B_34/" tstamps="/5AAA5765/"/>
      <tstamp>5A9737EE</tstamp>
    </comp>
    <comp ref="LED28">
      <value>WS2812B</value>
      <footprint>LEDs:LED_WS2812B-PLCC4</footprint>
      <libsource lib="Worldsemi" part="WS2812B"/>
      <sheetpath names="/WS2812B_35/" tstamps="/5AAA5769/"/>
      <tstamp>5A973791</tstamp>
    </comp>
    <comp ref="C33">
      <value>0.1u</value>
      <footprint>Capacitors_SMD:C_0603_HandSoldering</footprint>
      <libsource lib="device" part="C"/>
      <sheetpath names="/WS2812B_35/" tstamps="/5AAA5769/"/>
      <tstamp>5A9737EE</tstamp>
    </comp>
    <comp ref="LED29">
      <value>WS2812B</value>
      <footprint>LEDs:LED_WS2812B-PLCC4</footprint>
      <libsource lib="Worldsemi" part="WS2812B"/>
      <sheetpath names="/WS2812B_36/" tstamps="/5AAA576D/"/>
      <tstamp>5A973791</tstamp>
    </comp>
    <comp ref="C34">
      <value>0.1u</value>
      <footprint>Capacitors_SMD:C_0603_HandSoldering</footprint>
      <libsource lib="device" part="C"/>
      <sheetpath names="/WS2812B_36/" tstamps="/5AAA576D/"/>
      <tstamp>5A9737EE</tstamp>
    </comp>
    <comp ref="LED30">
      <value>WS2812B</value>
      <footprint>LEDs:LED_WS2812B-PLCC4</footprint>
      <libsource lib="Worldsemi" part="WS2812B"/>
      <sheetpath names="/WS2812B_37/" tstamps="/5AAA5776/"/>
      <tstamp>5A973791</tstamp>
    </comp>
    <comp ref="C35">
      <value>0.1u</value>
      <footprint>Capacitors_SMD:C_0603_HandSoldering</footprint>
      <libsource lib="device" part="C"/>
      <sheetpath names="/WS2812B_37/" tstamps="/5AAA5776/"/>
      <tstamp>5A9737EE</tstamp>
    </comp>
    <comp ref="LED31">
      <value>WS2812B</value>
      <footprint>LEDs:LED_WS2812B-PLCC4</footprint>
      <libsource lib="Worldsemi" part="WS2812B"/>
      <sheetpath names="/WS2812B_38/" tstamps="/5AAA577A/"/>
      <tstamp>5A973791</tstamp>
    </comp>
    <comp ref="C36">
      <value>0.1u</value>
      <footprint>Capacitors_SMD:C_0603_HandSoldering</footprint>
      <libsource lib="device" part="C"/>
      <sheetpath names="/WS2812B_38/" tstamps="/5AAA577A/"/>
      <tstamp>5A9737EE</tstamp>
    </comp>
    <comp ref="LED32">
      <value>WS2812B</value>
      <footprint>LEDs:LED_WS2812B-PLCC4</footprint>
      <libsource lib="Worldsemi" part="WS2812B"/>
      <sheetpath names="/WS2812B_25/" tstamps="/5AAA7755/"/>
      <tstamp>5A973791</tstamp>
    </comp>
    <comp ref="C37">
      <value>0.1u</value>
      <footprint>Capacitors_SMD:C_0603_HandSoldering</footprint>
      <libsource lib="device" part="C"/>
      <sheetpath names="/WS2812B_25/" tstamps="/5AAA7755/"/>
      <tstamp>5A9737EE</tstamp>
    </comp>
    <comp ref="LED33">
      <value>WS2812B</value>
      <footprint>LEDs:LED_WS2812B-PLCC4</footprint>
      <libsource lib="Worldsemi" part="WS2812B"/>
      <sheetpath names="/WS2812B_26/" tstamps="/5AAA7759/"/>
      <tstamp>5A973791</tstamp>
    </comp>
    <comp ref="C38">
      <value>0.1u</value>
      <footprint>Capacitors_SMD:C_0603_HandSoldering</footprint>
      <libsource lib="device" part="C"/>
      <sheetpath names="/WS2812B_26/" tstamps="/5AAA7759/"/>
      <tstamp>5A9737EE</tstamp>
    </comp>
    <comp ref="LED34">
      <value>WS2812B</value>
      <footprint>LEDs:LED_WS2812B-PLCC4</footprint>
      <libsource lib="Worldsemi" part="WS2812B"/>
      <sheetpath names="/WS2812B_27/" tstamps="/5AAA775D/"/>
      <tstamp>5A973791</tstamp>
    </comp>
    <comp ref="C39">
      <value>0.1u</value>
      <footprint>Capacitors_SMD:C_0603_HandSoldering</footprint>
      <libsource lib="device" part="C"/>
      <sheetpath names="/WS2812B_27/" tstamps="/5AAA775D/"/>
      <tstamp>5A9737EE</tstamp>
    </comp>
    <comp ref="LED35">
      <value>WS2812B</value>
      <footprint>LEDs:LED_WS2812B-PLCC4</footprint>
      <libsource lib="Worldsemi" part="WS2812B"/>
      <sheetpath names="/WS2812B_28/" tstamps="/5AAA7761/"/>
      <tstamp>5A973791</tstamp>
    </comp>
    <comp ref="C40">
      <value>0.1u</value>
      <footprint>Capacitors_SMD:C_0603_HandSoldering</footprint>
      <libsource lib="device" part="C"/>
      <sheetpath names="/WS2812B_28/" tstamps="/5AAA7761/"/>
      <tstamp>5A9737EE</tstamp>
    </comp>
    <comp ref="LED36">
      <value>WS2812B</value>
      <footprint>LEDs:LED_WS2812B-PLCC4</footprint>
      <libsource lib="Worldsemi" part="WS2812B"/>
      <sheetpath names="/WS2812B_29/" tstamps="/5AAA7765/"/>
      <tstamp>5A973791</tstamp>
    </comp>
    <comp ref="C41">
      <value>0.1u</value>
      <footprint>Capacitors_SMD:C_0603_HandSoldering</footprint>
      <libsource lib="device" part="C"/>
      <sheetpath names="/WS2812B_29/" tstamps="/5AAA7765/"/>
      <tstamp>5A9737EE</tstamp>
    </comp>
    <comp ref="LED37">
      <value>WS2812B</value>
      <footprint>LEDs:LED_WS2812B-PLCC4</footprint>
      <libsource lib="Worldsemi" part="WS2812B"/>
      <sheetpath names="/WS2812B_30/" tstamps="/5AAA776E/"/>
      <tstamp>5A973791</tstamp>
    </comp>
    <comp ref="C42">
      <value>0.1u</value>
      <footprint>Capacitors_SMD:C_0603_HandSoldering</footprint>
      <libsource lib="device" part="C"/>
      <sheetpath names="/WS2812B_30/" tstamps="/5AAA776E/"/>
      <tstamp>5A9737EE</tstamp>
    </comp>
    <comp ref="LED38">
      <value>WS2812B</value>
      <footprint>LEDs:LED_WS2812B-PLCC4</footprint>
      <libsource lib="Worldsemi" part="WS2812B"/>
      <sheetpath names="/WS2812B_31/" tstamps="/5AAA7772/"/>
      <tstamp>5A973791</tstamp>
    </comp>
    <comp ref="C43">
      <value>0.1u</value>
      <footprint>Capacitors_SMD:C_0603_HandSoldering</footprint>
      <libsource lib="device" part="C"/>
      <sheetpath names="/WS2812B_31/" tstamps="/5AAA7772/"/>
      <tstamp>5A9737EE</tstamp>
    </comp>
  </components>
  <libparts>
    <libpart lib="mylibrary" part="74AHCT1G125">
      <fields>
        <field name="Reference">U</field>
        <field name="Value">74AHCT1G125</field>
      </fields>
      <pins>
        <pin num="1" name="OE" type="input"/>
        <pin num="2" name="In" type="input"/>
        <pin num="3" name="GND" type="power_in"/>
        <pin num="4" name="Out" type="3state"/>
        <pin num="5" name="VCC" type="power_in"/>
      </pins>
    </libpart>
    <libpart lib="mylibrary" part="AP2112">
      <fields>
        <field name="Reference">U</field>
        <field name="Value">AP2112</field>
      </fields>
      <pins>
        <pin num="1" name="Vin" type="power_in"/>
        <pin num="2" name="GND" type="power_in"/>
        <pin num="3" name="EN" type="input"/>
        <pin num="5" name="Vout" type="power_out"/>
      </pins>
    </libpart>
    <libpart lib="device" part="C">
      <description>Unpolarized capacitor</description>
      <footprints>
        <fp>C_*</fp>
      </footprints>
      <fields>
        <field name="Reference">C</field>
        <field name="Value">C</field>
      </fields>
      <pins>
        <pin num="1" name="~" type="passive"/>
        <pin num="2" name="~" type="passive"/>
      </pins>
    </libpart>
    <libpart lib="mylibrary" part="CCS811">
      <fields>
        <field name="Reference">U</field>
        <field name="Value">CCS811</field>
      </fields>
      <pins>
        <pin num="1" name="ADDR" type="input"/>
        <pin num="2" name="nRESET" type="input"/>
        <pin num="3" name="nINT" type="input"/>
        <pin num="4" name="PWM" type="input"/>
        <pin num="5" name="SENSE" type="input"/>
        <pin num="6" name="VDD" type="input"/>
        <pin num="7" name="nWAKE" type="input"/>
        <pin num="9" name="SDA" type="input"/>
        <pin num="10" name="SCL" type="input"/>
        <pin num="EP" name="GND" type="input"/>
      </pins>
    </libpart>
    <libpart lib="device" part="CP">
      <description>Polarised capacitor</description>
      <footprints>
        <fp>CP_*</fp>
      </footprints>
      <fields>
        <field name="Reference">C</field>
        <field name="Value">CP</field>
      </fields>
      <pins>
        <pin num="1" name="~" type="passive"/>
        <pin num="2" name="~" type="passive"/>
      </pins>
    </libpart>
    <libpart lib="conn" part="Conn_01x03">
      <description>Generic connector, single row, 01x03</description>
      <docs>~</docs>
      <footprints>
        <fp>Connector*:*_??x*mm*</fp>
        <fp>Connector*:*1x??x*mm*</fp>
        <fp>Pin?Header?Straight?1X*</fp>
        <fp>Pin?Header?Angled?1X*</fp>
        <fp>Socket?Strip?Straight?1X*</fp>
        <fp>Socket?Strip?Angled?1X*</fp>
      </footprints>
      <fields>
        <field name="Reference">J</field>
        <field name="Value">Conn_01x03</field>
      </fields>
      <pins>
        <pin num="1" name="Pin_1" type="passive"/>
        <pin num="2" name="Pin_2" type="passive"/>
        <pin num="3" name="Pin_3" type="passive"/>
      </pins>
    </libpart>
    <libpart lib="ESP8266" part="ESP-12">
      <aliases>
        <alias>ESP-07v2</alias>
      </aliases>
      <description>ESP8266 ESP-12 module, 16 pins, 2mm, PCB antenna</description>
      <docs>http://l0l.org.uk/2014/12/esp8266-modules-hardware-guide-gotta-catch-em-all/</docs>
      <footprints>
        <fp>ESP-07*</fp>
        <fp>ESP-12*</fp>
      </footprints>
      <fields>
        <field name="Reference">U</field>
        <field name="Value">ESP-12</field>
      </fields>
      <pins>
        <pin num="1" name="REST" type="input"/>
        <pin num="2" name="ADC" type="passive"/>
        <pin num="3" name="CH_PD" type="input"/>
        <pin num="4" name="GPIO16" type="BiDi"/>
        <pin num="5" name="GPIO14" type="BiDi"/>
        <pin num="6" name="GPIO12" type="BiDi"/>
        <pin num="7" name="GPIO13" type="BiDi"/>
        <pin num="8" name="VCC" type="power_in"/>
        <pin num="9" name="GND" type="power_in"/>
        <pin num="10" name="GPIO15" type="BiDi"/>
        <pin num="11" name="GPIO2" type="BiDi"/>
        <pin num="12" name="GPIO0" type="BiDi"/>
        <pin num="13" name="GPIO4" type="BiDi"/>
        <pin num="14" name="GPIO5" type="BiDi"/>
        <pin num="15" name="RXD" type="input"/>
        <pin num="16" name="TXD" type="output"/>
      </pins>
    </libpart>
    <libpart lib="device" part="R">
      <description>Resistor</description>
      <footprints>
        <fp>R_*</fp>
        <fp>R_*</fp>
      </footprints>
      <fields>
        <field name="Reference">R</field>
        <field name="Value">R</field>
      </fields>
      <pins>
        <pin num="1" name="~" type="passive"/>
        <pin num="2" name="~" type="passive"/>
      </pins>
    </libpart>
    <libpart lib="mylibrary" part="SHT31-D">
      <fields>
        <field name="Reference">U</field>
        <field name="Value">SHT31-D</field>
      </fields>
      <pins>
        <pin num="1" name="SDA" type="BiDi"/>
        <pin num="2" name="ADDR" type="input"/>
        <pin num="3" name="ALERT" type="output"/>
        <pin num="4" name="SCL" type="BiDi"/>
        <pin num="5" name="VCC" type="power_in"/>
        <pin num="6" name="nRESET" type="input"/>
        <pin num="7" name="R" type="unspc"/>
        <pin num="8" name="GND" type="power_in"/>
      </pins>
    </libpart>
    <libpart lib="switches" part="SW_Push">
      <description>Push button switch, generic, two pins</description>
      <fields>
        <field name="Reference">SW</field>
        <field name="Value">SW_Push</field>
      </fields>
      <pins>
        <pin num="1" name="1" type="passive"/>
        <pin num="2" name="2" type="passive"/>
      </pins>
    </libpart>
    <libpart lib="conn" part="USB_OTG">
      <description>USB mini/micro connector</description>
      <footprints>
        <fp>USB*</fp>
      </footprints>
      <fields>
        <field name="Reference">J</field>
        <field name="Value">USB_OTG</field>
      </fields>
      <pins>
        <pin num="1" name="VBUS" type="power_in"/>
        <pin num="2" name="D-" type="passive"/>
        <pin num="3" name="D+" type="passive"/>
        <pin num="4" name="ID" type="passive"/>
        <pin num="5" name="GND" type="power_in"/>
        <pin num="6" name="Shield" type="passive"/>
      </pins>
    </libpart>
    <libpart lib="Worldsemi" part="WS2812B">
      <description>RGB LED with integrated controller</description>
      <docs>http://www.world-semi.com/uploads/soft/150522/1-150522091P5.pdf</docs>
      <fields>
        <field name="Reference">LED</field>
        <field name="Value">WS2812B</field>
        <field name="Footprint">LEDs:LED_WS2812B-PLCC4</field>
      </fields>
      <pins>
        <pin num="1" name="VDD" type="power_in"/>
        <pin num="2" name="DOUT" type="output"/>
        <pin num="3" name="VSS" type="power_in"/>
        <pin num="4" name="DIN" type="input"/>
      </pins>
    </libpart>
    <libpart lib="mylibrary" part="iAQ-Core">
      <fields>
        <field name="Reference">U</field>
        <field name="Value">iAQ-Core</field>
      </fields>
      <pins>
        <pin num="2" name="SCL" type="input"/>
        <pin num="3" name="GND" type="power_in"/>
        <pin num="4" name="SDA" type="input"/>
        <pin num="6" name="VCC" type="power_in"/>
      </pins>
    </libpart>
  </libparts>
  <libraries>
    <library logical="ESP8266">
      <uri>/usr/share/kicad/library/kicad-ESP8266/ESP8266.lib</uri>
    </library>
    <library logical="mylibrary">
      <uri>/home/harald/Basteln/KiCadLibrary/mylibrary.lib</uri>
    </library>
    <library logical="conn">
      <uri>/usr/share/kicad/library/conn.lib</uri>
    </library>
    <library logical="switches">
      <uri>/usr/share/kicad/library/switches.lib</uri>
    </library>
    <library logical="device">
      <uri>/usr/share/kicad/library/device.lib</uri>
    </library>
    <library logical="Worldsemi">
      <uri>/usr/share/kicad/library/Worldsemi.lib</uri>
    </library>
  </libraries>
  <nets>
    <net code="1" name="+3V3">
      <node ref="U6" pin="6"/>
      <node ref="C44" pin="1"/>
      <node ref="U6" pin="1"/>
      <node ref="R10" pin="1"/>
      <node ref="R9" pin="1"/>
      <node ref="R8" pin="1"/>
      <node ref="U1" pin="5"/>
      <node ref="C3" pin="2"/>
      <node ref="R1" pin="1"/>
      <node ref="R4" pin="1"/>
      <node ref="R5" pin="1"/>
      <node ref="R2" pin="1"/>
      <node ref="U2" pin="8"/>
      <node ref="C5" pin="1"/>
      <node ref="C2" pin="2"/>
      <node ref="U5" pin="5"/>
      <node ref="U4" pin="6"/>
    </net>
    <net code="2" name="/esp-12s/ESP_SCL">
      <node ref="U2" pin="14"/>
      <node ref="U4" pin="2"/>
      <node ref="U5" pin="4"/>
      <node ref="U6" pin="10"/>
      <node ref="R9" pin="2"/>
    </net>
    <net code="3" name="GND">
      <node ref="C7" pin="1"/>
      <node ref="LED2" pin="3"/>
      <node ref="LED25" pin="3"/>
      <node ref="C30" pin="1"/>
      <node ref="LED1" pin="3"/>
      <node ref="LED26" pin="3"/>
      <node ref="C6" pin="1"/>
      <node ref="C31" pin="1"/>
      <node ref="LED23" pin="3"/>
      <node ref="LED4" pin="3"/>
      <node ref="C9" pin="1"/>
      <node ref="LED24" pin="3"/>
      <node ref="C8" pin="1"/>
      <node ref="LED3" pin="3"/>
      <node ref="C29" pin="1"/>
      <node ref="U5" pin="7"/>
      <node ref="PROG1" pin="1"/>
      <node ref="C5" pin="2"/>
      <node ref="LED28" pin="3"/>
      <node ref="R6" pin="1"/>
      <node ref="U5" pin="8"/>
      <node ref="C2" pin="1"/>
      <node ref="C33" pin="1"/>
      <node ref="U2" pin="9"/>
      <node ref="U5" pin="2"/>
      <node ref="J1" pin="1"/>
      <node ref="LED29" pin="3"/>
      <node ref="LED27" pin="3"/>
      <node ref="U1" pin="2"/>
      <node ref="C32" pin="1"/>
      <node ref="C1" pin="1"/>
      <node ref="C3" pin="1"/>
      <node ref="RST1" pin="1"/>
      <node ref="LED17" pin="3"/>
      <node ref="C16" pin="1"/>
      <node ref="C22" pin="1"/>
      <node ref="LED11" pin="3"/>
      <node ref="LED12" pin="3"/>
      <node ref="LED18" pin="3"/>
      <node ref="C15" pin="1"/>
      <node ref="C23" pin="1"/>
      <node ref="LED10" pin="3"/>
      <node ref="C19" pin="1"/>
      <node ref="LED14" pin="3"/>
      <node ref="LED15" pin="3"/>
      <node ref="C20" pin="1"/>
      <node ref="C18" pin="1"/>
      <node ref="LED13" pin="3"/>
      <node ref="LED16" pin="3"/>
      <node ref="C17" pin="1"/>
      <node ref="C21" pin="1"/>
      <node ref="C11" pin="1"/>
      <node ref="LED7" pin="3"/>
      <node ref="LED21" pin="3"/>
      <node ref="C26" pin="1"/>
      <node ref="LED6" pin="3"/>
      <node ref="LED22" pin="3"/>
      <node ref="C27" pin="1"/>
      <node ref="LED5" pin="3"/>
      <node ref="C10" pin="1"/>
      <node ref="C28" pin="1"/>
      <node ref="C14" pin="1"/>
      <node ref="LED19" pin="3"/>
      <node ref="LED9" pin="3"/>
      <node ref="C24" pin="1"/>
      <node ref="LED8" pin="3"/>
      <node ref="C13" pin="1"/>
      <node ref="LED20" pin="3"/>
      <node ref="C25" pin="1"/>
      <node ref="C12" pin="1"/>
      <node ref="LED37" pin="3"/>
      <node ref="C41" pin="1"/>
      <node ref="LED36" pin="3"/>
      <node ref="C37" pin="1"/>
      <node ref="LED32" pin="3"/>
      <node ref="C42" pin="1"/>
      <node ref="LED31" pin="3"/>
      <node ref="U6" pin="7"/>
      <node ref="U6" pin="EP"/>
      <node ref="C36" pin="1"/>
      <node ref="LED35" pin="3"/>
      <node ref="LED34" pin="3"/>
      <node ref="C39" pin="1"/>
      <node ref="C4" pin="2"/>
      <node ref="C38" pin="1"/>
      <node ref="C40" pin="1"/>
      <node ref="U3" pin="1"/>
      <node ref="LED33" pin="3"/>
      <node ref="U3" pin="3"/>
      <node ref="C35" pin="1"/>
      <node ref="C45" pin="2"/>
      <node ref="LED38" pin="3"/>
      <node ref="U4" pin="3"/>
      <node ref="C34" pin="1"/>
      <node ref="C44" pin="2"/>
      <node ref="C43" pin="1"/>
      <node ref="LED30" pin="3"/>
      <node ref="J2" pin="5"/>
    </net>
    <net code="4" name="Net-(U5-Pad6)">
      <node ref="U5" pin="6"/>
    </net>
    <net code="5" name="Net-(U5-Pad3)">
      <node ref="U5" pin="3"/>
    </net>
    <net code="6" name="/esp-12s/GPIO16">
      <node ref="U2" pin="4"/>
    </net>
    <net code="7" name="/esp-12s/ADC">
      <node ref="U2" pin="2"/>
    </net>
    <net code="8" name="/WS2812B_30/DIn">
      <node ref="LED37" pin="4"/>
      <node ref="LED36" pin="2"/>
    </net>
    <net code="9" name="/WS2812B_31/DIn">
      <node ref="LED38" pin="4"/>
      <node ref="LED37" pin="2"/>
    </net>
    <net code="10" name="/WS2812B_31/DOut">
      <node ref="LED38" pin="2"/>
    </net>
    <net code="11" name="/WS2812B_25/DIn">
      <node ref="LED32" pin="4"/>
      <node ref="LED31" pin="2"/>
    </net>
    <net code="12" name="/esp-12s/GPIO12">
      <node ref="U2" pin="6"/>
    </net>
    <net code="13" name="Net-(R10-Pad2)">
      <node ref="R10" pin="2"/>
      <node ref="U6" pin="2"/>
    </net>
    <net code="14" name="Net-(U6-Pad3)">
      <node ref="U6" pin="3"/>
    </net>
    <net code="15" name="/esp-12s/ESP_SDA">
      <node ref="U5" pin="1"/>
      <node ref="U2" pin="13"/>
      <node ref="U4" pin="4"/>
      <node ref="U6" pin="9"/>
      <node ref="R8" pin="2"/>
    </net>
    <net code="16" name="/WS2812B_32/DIn">
      <node ref="LED25" pin="4"/>
      <node ref="LED24" pin="2"/>
    </net>
    <net code="17" name="/WS2812B_20/DIn">
      <node ref="LED19" pin="2"/>
      <node ref="LED20" pin="4"/>
    </net>
    <net code="18" name="Net-(J2-Pad6)">
      <node ref="J2" pin="6"/>
    </net>
    <net code="19" name="Net-(J2-Pad4)">
      <node ref="J2" pin="4"/>
    </net>
    <net code="20" name="Net-(J2-Pad2)">
      <node ref="J2" pin="2"/>
    </net>
    <net code="21" name="Net-(J2-Pad3)">
      <node ref="J2" pin="3"/>
    </net>
    <net code="22" name="+5V">
      <node ref="C43" pin="2"/>
      <node ref="LED19" pin="1"/>
      <node ref="C24" pin="2"/>
      <node ref="C34" pin="2"/>
      <node ref="LED16" pin="1"/>
      <node ref="C21" pin="2"/>
      <node ref="LED30" pin="1"/>
      <node ref="LED17" pin="1"/>
      <node ref="LED15" pin="1"/>
      <node ref="C20" pin="2"/>
      <node ref="LED29" pin="1"/>
      <node ref="C35" pin="2"/>
      <node ref="LED18" pin="1"/>
      <node ref="C23" pin="2"/>
      <node ref="C22" pin="2"/>
      <node ref="C31" pin="2"/>
      <node ref="LED26" pin="1"/>
      <node ref="LED33" pin="1"/>
      <node ref="C38" pin="2"/>
      <node ref="C28" pin="2"/>
      <node ref="C41" pin="2"/>
      <node ref="LED34" pin="1"/>
      <node ref="LED25" pin="1"/>
      <node ref="C30" pin="2"/>
      <node ref="C39" pin="2"/>
      <node ref="LED23" pin="1"/>
      <node ref="C40" pin="2"/>
      <node ref="LED35" pin="1"/>
      <node ref="LED24" pin="1"/>
      <node ref="C29" pin="2"/>
      <node ref="C26" pin="2"/>
      <node ref="C37" pin="2"/>
      <node ref="LED21" pin="1"/>
      <node ref="LED28" pin="1"/>
      <node ref="LED37" pin="1"/>
      <node ref="LED20" pin="1"/>
      <node ref="C25" pin="2"/>
      <node ref="LED31" pin="1"/>
      <node ref="C36" pin="2"/>
      <node ref="LED38" pin="1"/>
      <node ref="C32" pin="2"/>
      <node ref="LED27" pin="1"/>
      <node ref="LED36" pin="1"/>
      <node ref="LED22" pin="1"/>
      <node ref="C27" pin="2"/>
      <node ref="C33" pin="2"/>
      <node ref="C42" pin="2"/>
      <node ref="LED32" pin="1"/>
      <node ref="LED6" pin="1"/>
      <node ref="C11" pin="2"/>
      <node ref="LED5" pin="1"/>
      <node ref="C10" pin="2"/>
      <node ref="LED4" pin="1"/>
      <node ref="C9" pin="2"/>
      <node ref="LED9" pin="1"/>
      <node ref="C14" pin="2"/>
      <node ref="C13" pin="2"/>
      <node ref="LED3" pin="1"/>
      <node ref="LED8" pin="1"/>
      <node ref="LED7" pin="1"/>
      <node ref="C12" pin="2"/>
      <node ref="U1" pin="1"/>
      <node ref="C1" pin="2"/>
      <node ref="C4" pin="1"/>
      <node ref="U3" pin="5"/>
      <node ref="J2" pin="1"/>
      <node ref="C45" pin="1"/>
      <node ref="C8" pin="2"/>
      <node ref="C7" pin="2"/>
      <node ref="LED2" pin="1"/>
      <node ref="LED1" pin="1"/>
      <node ref="C6" pin="2"/>
      <node ref="R3" pin="2"/>
      <node ref="C19" pin="2"/>
      <node ref="LED12" pin="1"/>
      <node ref="C17" pin="2"/>
      <node ref="C18" pin="2"/>
      <node ref="LED14" pin="1"/>
      <node ref="C16" pin="2"/>
      <node ref="LED11" pin="1"/>
      <node ref="LED13" pin="1"/>
      <node ref="C15" pin="2"/>
      <node ref="LED10" pin="1"/>
    </net>
    <net code="23" name="/esp-12s/GPIO13">
      <node ref="U2" pin="7"/>
    </net>
    <net code="24" name="Net-(U6-Pad4)">
      <node ref="U6" pin="4"/>
      <node ref="U6" pin="5"/>
    </net>
    <net code="25" name="/WS2812B_11/DIn">
      <node ref="LED10" pin="2"/>
      <node ref="LED11" pin="4"/>
    </net>
    <net code="26" name="/WS2812B_10/DIn">
      <node ref="LED10" pin="4"/>
      <node ref="LED9" pin="2"/>
    </net>
    <net code="27" name="/WS2812B_12/DIn">
      <node ref="LED11" pin="2"/>
      <node ref="LED12" pin="4"/>
    </net>
    <net code="28" name="/WS2812B_08/DIn">
      <node ref="LED7" pin="2"/>
      <node ref="LED8" pin="4"/>
    </net>
    <net code="29" name="/WS2812B_07/DIn">
      <node ref="LED7" pin="4"/>
      <node ref="LED6" pin="2"/>
    </net>
    <net code="30" name="/WS2812B_06/DIn">
      <node ref="LED5" pin="2"/>
      <node ref="LED6" pin="4"/>
    </net>
    <net code="31" name="/WS2812B_05/DIn">
      <node ref="LED4" pin="2"/>
      <node ref="LED5" pin="4"/>
    </net>
    <net code="32" name="/WS2812B_22/DIn">
      <node ref="LED22" pin="4"/>
      <node ref="LED21" pin="2"/>
    </net>
    <net code="33" name="/WS2812B_21/DIn">
      <node ref="LED21" pin="4"/>
      <node ref="LED20" pin="2"/>
    </net>
    <net code="34" name="/WS2812B_18/DIn">
      <node ref="LED17" pin="2"/>
      <node ref="LED18" pin="4"/>
    </net>
    <net code="35" name="/WS2812B_19/DIn">
      <node ref="LED19" pin="4"/>
      <node ref="LED18" pin="2"/>
    </net>
    <net code="36" name="/WS2812B_17/DIn">
      <node ref="LED16" pin="2"/>
      <node ref="LED17" pin="4"/>
    </net>
    <net code="37" name="/WS2812B_04/DIn">
      <node ref="LED4" pin="4"/>
      <node ref="LED3" pin="2"/>
    </net>
    <net code="38" name="/WS2812B_16/DIn">
      <node ref="LED16" pin="4"/>
      <node ref="LED15" pin="2"/>
    </net>
    <net code="39" name="/WS2812B_15/DIn">
      <node ref="LED14" pin="2"/>
      <node ref="LED15" pin="4"/>
    </net>
    <net code="40" name="/WS2812B_13/DIn">
      <node ref="LED12" pin="2"/>
      <node ref="LED13" pin="4"/>
    </net>
    <net code="41" name="/WS2812B_14/DIn">
      <node ref="LED13" pin="2"/>
      <node ref="LED14" pin="4"/>
    </net>
    <net code="42" name="Net-(R7-Pad2)">
      <node ref="R7" pin="2"/>
      <node ref="U3" pin="4"/>
    </net>
    <net code="44" name="/esp-12s/GPIO14">
      <node ref="U3" pin="2"/>
      <node ref="U2" pin="5"/>
    </net>
    <net code="45" name="/WS2812B_03/DIn">
      <node ref="LED3" pin="4"/>
      <node ref="LED2" pin="2"/>
    </net>
    <net code="46" name="/WS2812B_01/DIn">
      <node ref="R7" pin="1"/>
      <node ref="LED1" pin="4"/>
    </net>
    <net code="47" name="/WS2812B_02/DIn">
      <node ref="LED1" pin="2"/>
      <node ref="LED2" pin="4"/>
    </net>
    <net code="48" name="/WS2812B_28/DIn">
      <node ref="LED34" pin="2"/>
      <node ref="LED35" pin="4"/>
    </net>
    <net code="49" name="/WS2812B_34/DIn">
      <node ref="LED26" pin="2"/>
      <node ref="LED27" pin="4"/>
    </net>
    <net code="50" name="/WS2812B_38/DIn">
      <node ref="LED31" pin="4"/>
      <node ref="LED30" pin="2"/>
    </net>
    <net code="51" name="/WS2812B_36/DIn">
      <node ref="LED29" pin="4"/>
      <node ref="LED28" pin="2"/>
    </net>
    <net code="52" name="/WS2812B_35/DIn">
      <node ref="LED28" pin="4"/>
      <node ref="LED27" pin="2"/>
    </net>
    <net code="53" name="/WS2812B_33/DIn">
      <node ref="LED25" pin="2"/>
      <node ref="LED26" pin="4"/>
    </net>
    <net code="54" name="/WS2812B_37/DIn">
      <node ref="LED30" pin="4"/>
      <node ref="LED29" pin="2"/>
    </net>
    <net code="55" name="/WS2812B_29/DIn">
      <node ref="LED35" pin="2"/>
      <node ref="LED36" pin="4"/>
    </net>
    <net code="56" name="/WS2812B_27/DIn">
      <node ref="LED34" pin="4"/>
      <node ref="LED33" pin="2"/>
    </net>
    <net code="57" name="/WS2812B_26/DIn">
      <node ref="LED33" pin="4"/>
      <node ref="LED32" pin="2"/>
    </net>
    <net code="58" name="/WS2812B_09/DIn">
      <node ref="LED8" pin="2"/>
      <node ref="LED9" pin="4"/>
    </net>
    <net code="59" name="/WS2812B_24/DIn">
      <node ref="LED24" pin="4"/>
      <node ref="LED23" pin="2"/>
    </net>
    <net code="60" name="/WS2812B_23/DIn">
      <node ref="LED22" pin="2"/>
      <node ref="LED23" pin="4"/>
    </net>
    <net code="61" name="Net-(PROG1-Pad2)">
      <node ref="U2" pin="12"/>
      <node ref="R4" pin="2"/>
      <node ref="PROG1" pin="2"/>
    </net>
    <net code="62" name="Net-(R5-Pad2)">
      <node ref="R5" pin="2"/>
      <node ref="U2" pin="11"/>
    </net>
    <net code="63" name="Net-(R6-Pad2)">
      <node ref="R6" pin="2"/>
      <node ref="U2" pin="10"/>
    </net>
    <net code="64" name="Net-(R1-Pad2)">
      <node ref="R1" pin="2"/>
      <node ref="U2" pin="3"/>
    </net>
    <net code="65" name="/esp-12s/ESP_TX">
      <node ref="J1" pin="3"/>
      <node ref="U2" pin="16"/>
    </net>
    <net code="66" name="/esp-12s/ESP_RX">
      <node ref="U2" pin="15"/>
      <node ref="J1" pin="2"/>
    </net>
    <net code="67" name="Net-(R2-Pad2)">
      <node ref="RST1" pin="2"/>
      <node ref="U2" pin="1"/>
      <node ref="R2" pin="2"/>
    </net>
    <net code="68" name="Net-(R3-Pad1)">
      <node ref="U1" pin="3"/>
      <node ref="R3" pin="1"/>
    </net>
  </nets>
</export>
